linkml_data_qc/__init__.py
linkml_data_qc/_version.py
linkml_data_qc/analyzer.py
linkml_data_qc/cli.py
linkml_data_qc/config.py
linkml_data_qc/dashboard.py
linkml_data_qc/formatters.py
linkml_data_qc/html_dashboard.py
linkml_data_qc/introspector.py
linkml_data_qc/models.py
linkml_data_qc-0.1.0.dist-info/METADATA
linkml_data_qc-0.1.0.dist-info/WHEEL
linkml_data_qc-0.1.0.dist-info/entry_points.txt
linkml_data_qc-0.1.0.dist-info/licenses/LICENSE
linkml_data_qc-0.1.0.dist-info/RECORD
