Metadata-Version: 2.4
Name: linkml_data_qc
Version: 0.1.0
Summary: Compliance analysis tool for LinkML data files - measures recommended field population.
Author-email: My Name <my-name@my-org.org>
License-Expression: Apache-2.0
License-File: LICENSE
Requires-Python: <4.0,>=3.10
Requires-Dist: linkml-runtime>=1.9.4
Requires-Dist: pydantic>=2.0.0
Requires-Dist: pyyaml>=6.0
Requires-Dist: typer>=0.9.0
Provides-Extra: viz
Requires-Dist: matplotlib>=3.7.0; extra == 'viz'
Requires-Dist: seaborn>=0.13.0; extra == 'viz'
